tests/__init__.py
tests/test_codeshakespeare.py
CodeShakespeare-0.1.2.dist-info/LICENSE
CodeShakespeare-0.1.2.dist-info/METADATA
CodeShakespeare-0.1.2.dist-info/WHEEL
CodeShakespeare-0.1.2.dist-info/top_level.txt
CodeShakespeare-0.1.2.dist-info/RECORD
