Metadata-Version: 2.1
Name: CodeShakespeare
Version: 0.1.2
Summary: A package for generating Shakespearean-style quotes and comments
Home-page: https://github.com/software-students-fall2024/3-python-package-wear
Author: Emilt Huang, Reese Burns, Wenli Shi, Alex Hsu
Author-email: eh96@nyu.edu
Classifier: Programming Language :: Python :: 3
Classifier: Programming Language :: Python :: 3.8
Classifier: Programming Language :: Python :: 3.9
Classifier: Programming Language :: Python :: 3.10
Classifier: Programming Language :: Python :: 3.11
Classifier: License :: OSI Approved :: MIT License
Classifier: Operating System :: OS Independent
Requires-Python: >=3.8
License-File: LICENSE
